prunerr/__init__.py
prunerr/__main__.py
prunerr/downloadclient.py
prunerr/downloaditem.py
prunerr/operations.py
prunerr/py.typed
prunerr/runner.py
prunerr/servarr.py
prunerr/utils.py
prunerr/version.py
prunerr/home/.config/prunerr.yml
prunerr-2.0.0.dist-info/.gitignore
prunerr-2.0.0.dist-info/METADATA
prunerr-2.0.0.dist-info/WHEEL
prunerr-2.0.0.dist-info/entry_points.txt
prunerr-2.0.0.dist-info/top_level.txt
prunerr-2.0.0.dist-info/RECORD
