Metadata-Version: 2.1
Name: prunerr
Version: 2.0.0
Summary: Perma-seed Servarr media libraries
Home-page: https://gitlab.com/rpatterson/prunerr
Author: Ross Patterson
Author-email: me@rpatterson.net
License: MIT
Keywords: servarr,sonarr,radarr,transmission,bittorent,torrent
Classifier: Development Status :: 4 - Beta
Classifier: Environment :: Console
Classifier: Intended Audience :: End Users/Desktop
Classifier: License :: OSI Approved :: MIT License
Classifier: Natural Language :: English
Classifier: Operating System :: OS Independent
Classifier: Programming Language :: Python :: 3
Classifier: Programming Language :: Python :: 3.11
Classifier: Programming Language :: Python :: 3.12
Classifier: Programming Language :: Python :: 3.10
Classifier: Programming Language :: Python :: 3.9
Classifier: Programming Language :: Python :: 3.8
Classifier: Programming Language :: Python :: 3 :: Only
Classifier: Topic :: Communications :: File Sharing
Classifier: Topic :: Internet
Requires-Python: >=3.8
Requires-Dist: argcomplete
Requires-Dist: transmission-rpc <4
Requires-Dist: service-logging
Requires-Dist: pyyaml
Requires-Dist: arrapi >=1.2
Requires-Dist: tenacity
Requires-Dist: pathlib3x ; python_version < "3.10"
Requires-Dist: backports.cached-property ; python_version < "3.8"
Provides-Extra: devel
Requires-Dist: prospector[with_everything] ; extra == 'devel'
Requires-Dist: xenon ; extra == 'devel'
Requires-Dist: black ; extra == 'devel'
Requires-Dist: autoflake ; extra == 'devel'
Requires-Dist: autopep8 ; extra == 'devel'
Requires-Dist: types-PyYAML ; extra == 'devel'
Requires-Dist: build ; extra == 'devel'
Provides-Extra: test
Requires-Dist: requests-mock ; extra == 'test'
Requires-Dist: pytest ; extra == 'test'
Requires-Dist: coverage ; extra == 'test'
Requires-Dist: pip-tools ; extra == 'test'
